metashape/__init__.py
metashape/__main__.py
metashape/_access.py
metashape/_dataclass.py
metashape/_typeinfo.py
metashape/_typeinfo_evil.py
metashape/_typeinfo_evil.pyi
metashape/cli.py
metashape/constants.py
metashape/declarative.py
metashape/langhelpers.py
metashape/marker.py
metashape/name.py
metashape/py.typed
metashape/runtime.py
metashape/typeinfo.py
metashape/types.py
metashape/analyze/__init__.py
metashape/analyze/collector.py
metashape/analyze/config.py
metashape/analyze/resolver.py
metashape/analyze/scan.py
metashape/analyze/walker.py
metashape/inputs/__init__.py
metashape/inputs/python/__init__.py
metashape/inputs/python/__main__.py
metashape/outputs/__init__.py
metashape/outputs/graphql/__init__.py
metashape/outputs/graphql/__main__.py
metashape/outputs/graphql/_prestring.py
metashape/outputs/graphql/detect.py
metashape/outputs/graphql/emit.py
metashape/outputs/jsonschema/__init__.py
metashape/outputs/jsonschema/__main__.py
metashape/outputs/jsonschema/detect.py
metashape/outputs/jsonschema/emit.py
metashape/outputs/openapi/__init__.py
metashape/outputs/openapi/__main__.py
metashape/outputs/openapi/detect.py
metashape/outputs/openapi/emit.py
metashape/outputs/openapi/types.py
metashape/outputs/raw/__init__.py
metashape/outputs/raw/__main__.py
metashape/outputs/raw/emit.py
metashape/tests/outputs/__init__.py
metashape/tests/outputs/openapi/__init__.py
metashape/tests/outputs/openapi/test_detect.py
metashape-0.0.4.dist-info/METADATA
metashape-0.0.4.dist-info/WHEEL
metashape-0.0.4.dist-info/top_level.txt
metashape-0.0.4.dist-info/RECORD
