Metadata-Version: 2.1
Name: metashape
Version: 0.0.4
Summary: -
Home-page: https://github.com/podhmo/metashape
Author: podhmo
Author-email: ababjam61+github@gmail.com
License: UNKNOWN
Platform: UNKNOWN
Classifier: Programming Language :: Python :: 3
Classifier: Development Status :: 3 - Alpha
Requires-Python: >3.7
Requires-Dist: typing-extensions
Requires-Dist: dictknife
Provides-Extra: cli
Requires-Dist: json2python-models ; extra == 'cli'
Requires-Dist: dictknife (>=0.13.0) ; extra == 'cli'
Requires-Dist: prestring (>=0.9.0) ; extra == 'cli'
Requires-Dist: magicalimport ; extra == 'cli'
Requires-Dist: magicalimport (>=0.9.1) ; extra == 'cli'
Provides-Extra: dev
Requires-Dist: pytest ; extra == 'dev'
Requires-Dist: magicalimport ; extra == 'dev'
Requires-Dist: black ; extra == 'dev'
Requires-Dist: flake8 ; extra == 'dev'
Requires-Dist: mypy ; extra == 'dev'
Provides-Extra: input
Requires-Dist: json2python-models ; extra == 'input'
Provides-Extra: output
Requires-Dist: dictknife (>=0.13.0) ; extra == 'output'
Requires-Dist: prestring (>=0.9.0) ; extra == 'output'
Requires-Dist: magicalimport ; extra == 'output'
Provides-Extra: testing
Requires-Dist: pytest ; extra == 'testing'
Requires-Dist: magicalimport ; extra == 'testing'
